nlpknife/__init__.py
nlpknife/logger.py
nlpknife/search.py
nlpknife/timer.py
nlpknife/db/__init__.py
nlpknife/db/es_helper.py
nlpknife/db/minio_helper.py
nlpknife/db/mysql_helper.py
nlpknife/db/neo4j_helper.py
nlpknife/db/redis_helper.py
nlpknife/evaluation/__init__.py
nlpknife/evaluation/ner_evaluation.py
nlpknife/evaluation/rag_evaluation.py
nlpknife/evaluation/ner_eval_core/__init__.py
nlpknife/evaluation/ner_eval_core/ner_eval.py
nlpknife/extractor/__init__.py
nlpknife/extractor/json_helper.py
nlpknife/message/__init__.py
nlpknife-0.0.4.dist-info/LICENSE
nlpknife-0.0.4.dist-info/METADATA
nlpknife-0.0.4.dist-info/WHEEL
nlpknife-0.0.4.dist-info/top_level.txt
nlpknife-0.0.4.dist-info/RECORD
