Metadata-Version: 2.1
Name: nlpknife
Version: 0.0.4
Summary: my nlpknife
Home-page: https://github.com/zhpmatrix/nlpknife
Author: zhpmatrix
License: UNKNOWN
Download-URL: https://pypi.tuna.tsinghua.edu.cn/simple
Platform: UNKNOWN
Requires-Python: >=3.7
License-File: LICENSE
Requires-Dist: setuptools ==58.2.0
Requires-Dist: wheel ==0.43.0
Requires-Dist: pymysql
Requires-Dist: py2neo
Requires-Dist: pandas
Requires-Dist: redis
Requires-Dist: baidusearch
Requires-Dist: gunicorn
Requires-Dist: gevent
